AUTHORS.rst
CONTRIBUTING.rst
HISTORY.rst
LICENSE
MANIFEST.in
README.rst
requirements.txt
setup.cfg
setup.py
test_requirements.txt
lib/orderedset/__init__.py
lib/orderedset/_orderedset.c
lib/orderedset/_orderedset.pyx
lib/orderedset.egg-info/PKG-INFO
lib/orderedset.egg-info/SOURCES.txt
lib/orderedset.egg-info/dependency_links.txt
lib/orderedset.egg-info/not-zip-safe
lib/orderedset.egg-info/top_level.txt